<annotation>
    <folder>VOCType</folder>
    <filename>000405.jpg</filename>
    <source>
        <database>VOC</database>
    </source>
    <size>
        <width>936</width>
        <height>537</height>
        <depth>3</depth>
    </size>
    <segmented>0</segmented>
    <object>
        <name>window</name>
        <pose>Unspecified</pose>
        <truncated>0</truncated>
        <difficult>0</difficult>
        <bndbox>
            <xmin>141</xmin>
            <ymin>91</ymin>
            <xmax>202</xmax>
            <ymax>184</ymax>
        </bndbox>
    </object>
    <object>
        <name>window</name>
        <pose>Unspecified</pose>
        <truncated>0</truncated>
        <difficult>0</difficult>
        <bndbox>
            <xmin>229</xmin>
            <ymin>103</ymin>
            <xmax>277</xmax>
            <ymax>186</ymax>
        </bndbox>
    </object>
    <object>
        <name>window</name>
        <pose>Unspecified</pose>
        <truncated>0</truncated>
        <difficult>0</difficult>
        <bndbox>
            <xmin>136</xmin>
            <ymin>198</ymin>
            <xmax>198</xmax>
            <ymax>272</ymax>
        </bndbox>
    </object>
    <object>
        <name>window</name>
        <pose>Unspecified</pose>
        <truncated>0</truncated>
        <difficult>0</difficult>
        <bndbox>
            <xmin>225</xmin>
            <ymin>205</ymin>
            <xmax>277</xmax>
            <ymax>271</ymax>
        </bndbox>
    </object>
    <object>
        <name>window</name>
        <pose>Unspecified</pose>
        <truncated>0</truncated>
        <difficult>0</difficult>
        <bndbox>
            <xmin>148</xmin>
            <ymin>2</ymin>
            <xmax>209</xmax>
            <ymax>75</ymax>
        </bndbox>
    </object>
    <object>
        <name>window</name>
        <pose>Unspecified</pose>
        <truncated>0</truncated>
        <difficult>0</difficult>
        <bndbox>
            <xmin>232</xmin>
            <ymin>10</ymin>
            <xmax>289</xmax>
            <ymax>89</ymax>
        </bndbox>
    </object>
</annotation>
