<annotation>
    <folder>VOCType</folder>
    <filename>001137.jpg</filename>
    <source>
        <database>VOC</database>
    </source>
    <size>
        <width>936</width>
        <height>537</height>
        <depth>3</depth>
    </size>
    <segmented>0</segmented>
    <object>
        <name>window</name>
        <pose>Unspecified</pose>
        <truncated>0</truncated>
        <difficult>0</difficult>
        <bndbox>
            <xmin>618</xmin>
            <ymin>22</ymin>
            <xmax>739</xmax>
            <ymax>212</ymax>
        </bndbox>
    </object>
    <object>
        <name>window</name>
        <pose>Unspecified</pose>
        <truncated>0</truncated>
        <difficult>0</difficult>
        <bndbox>
            <xmin>818</xmin>
            <ymin>30</ymin>
            <xmax>936</xmax>
            <ymax>213</ymax>
        </bndbox>
    </object>
    <object>
        <name>window</name>
        <pose>Unspecified</pose>
        <truncated>0</truncated>
        <difficult>0</difficult>
        <bndbox>
            <xmin>350</xmin>
            <ymin>17</ymin>
            <xmax>476</xmax>
            <ymax>203</ymax>
        </bndbox>
    </object>
    <object>
        <name>window</name>
        <pose>Unspecified</pose>
        <truncated>0</truncated>
        <difficult>0</difficult>
        <bndbox>
            <xmin>141</xmin>
            <ymin>12</ymin>
            <xmax>276</xmax>
            <ymax>201</ymax>
        </bndbox>
    </object>
</annotation>
